pyunifiprotect/__init__.py
pyunifiprotect/__main__.py
pyunifiprotect/api.py
pyunifiprotect/exceptions.py
pyunifiprotect/py.typed
pyunifiprotect/pydantic_compat.py
pyunifiprotect/session.py
pyunifiprotect/stream.py
pyunifiprotect/utils.py
pyunifiprotect/websocket.py
pyunifiprotect/cli/__init__.py
pyunifiprotect/cli/backup.py
pyunifiprotect/cli/base.py
pyunifiprotect/cli/cameras.py
pyunifiprotect/cli/chimes.py
pyunifiprotect/cli/doorlocks.py
pyunifiprotect/cli/events.py
pyunifiprotect/cli/lights.py
pyunifiprotect/cli/liveviews.py
pyunifiprotect/cli/nvr.py
pyunifiprotect/cli/sensors.py
pyunifiprotect/cli/viewers.py
pyunifiprotect/data/__init__.py
pyunifiprotect/data/base.py
pyunifiprotect/data/bootstrap.py
pyunifiprotect/data/convert.py
pyunifiprotect/data/devices.py
pyunifiprotect/data/nvr.py
pyunifiprotect/data/types.py
pyunifiprotect/data/user.py
pyunifiprotect/data/websocket.py
pyunifiprotect/test_util/__init__.py
pyunifiprotect/test_util/anonymize.py
pyunifiprotect-6.0.1.dist-info/METADATA
pyunifiprotect-6.0.1.dist-info/WHEEL
pyunifiprotect-6.0.1.dist-info/entry_points.txt
pyunifiprotect-6.0.1.dist-info/licenses/LICENSE
pyunifiprotect-6.0.1.dist-info/licenses/LICENSE.CHANGE
pyunifiprotect-6.0.1.dist-info/RECORD
