Metadata-Version: 2.3
Name: pyunifiprotect
Version: 6.0.1
Summary: Unofficial UniFi Protect Python API and CLI
Project-URL: Source Code, https://github.com/AngellusMortis/pyunifiprotect/
Project-URL: Documentation, https://angellusmortis.github.io/pyunifiprotect/latest/
Project-URL: Bug Reports, https://github.com/AngellusMortis/pyunifiprotect/issues/
Project-URL: Changelog, https://github.com/AngellusMortis/pyunifiprotect/releases/
Author-email: Bjarne Riis <bjarne@briis.com>, Christopher Bailey <cbailey@mort.is>
Maintainer-email: Christopher Bailey <cbailey@mort.is>, "J. Nick Koston" <nick@koston.org>
License: Business Source License
License-File: LICENSE
License-File: LICENSE.CHANGE
Keywords: Home Assistant,Python,Surveilance,UniFi,UniFi Protect,UniFiProtect
Classifier: Development Status :: 5 - Production/Stable
Classifier: Intended Audience :: Developers
Classifier: Programming Language :: Python :: 3.9
Classifier: Programming Language :: Python :: 3.10
Classifier: Programming Language :: Python :: 3.11
Classifier: Programming Language :: Python :: 3.12
Classifier: Topic :: Software Development :: Build Tools
Requires-Python: >=3.9
Requires-Dist: aiofiles
Requires-Dist: aiohttp
Requires-Dist: aioshutil
Requires-Dist: async-timeout; python_version < '3.11'
Requires-Dist: dateparser
Requires-Dist: orjson
Requires-Dist: packaging
Requires-Dist: pillow
Requires-Dist: platformdirs
Requires-Dist: pydantic!=1.9.1
Requires-Dist: pyjwt
Requires-Dist: typer[all]>0.6
Requires-Dist: yarl>=1.9
Provides-Extra: backup
Requires-Dist: aiosqlite; extra == 'backup'
Requires-Dist: asyncify; extra == 'backup'
Requires-Dist: av; extra == 'backup'
Requires-Dist: sqlalchemy[asyncio]; extra == 'backup'
Provides-Extra: dev
Requires-Dist: base36; extra == 'dev'
Requires-Dist: black; extra == 'dev'
Requires-Dist: build; extra == 'dev'
Requires-Dist: coverage[toml]; extra == 'dev'
Requires-Dist: ipython<8.19; extra == 'dev'
Requires-Dist: isort; extra == 'dev'
Requires-Dist: mike; extra == 'dev'
Requires-Dist: mkdocs-git-revision-date-localized-plugin; extra == 'dev'
Requires-Dist: mkdocs-include-markdown-plugin; extra == 'dev'
Requires-Dist: mkdocs-material; extra == 'dev'
Requires-Dist: mkdocstrings[python]; extra == 'dev'
Requires-Dist: mypy; extra == 'dev'
Requires-Dist: pydocstyle; extra == 'dev'
Requires-Dist: pytest; extra == 'dev'
Requires-Dist: pytest-asyncio; extra == 'dev'
Requires-Dist: pytest-benchmark; extra == 'dev'
Requires-Dist: pytest-cov; extra == 'dev'
Requires-Dist: pytest-sugar; extra == 'dev'
Requires-Dist: pytest-timeout>=1.2.1; extra == 'dev'
Requires-Dist: pytest-xdist[psutil]; extra == 'dev'
Requires-Dist: ruff; extra == 'dev'
Requires-Dist: sqlalchemy[asyncio,mypy]; extra == 'dev'
Requires-Dist: termcolor; extra == 'dev'
Requires-Dist: types-aiofiles; extra == 'dev'
Requires-Dist: types-dateparser; extra == 'dev'
Requires-Dist: types-pillow; extra == 'dev'
Requires-Dist: types-pyjwt; extra == 'dev'
Requires-Dist: types-termcolor; extra == 'dev'
Requires-Dist: tzdata; extra == 'dev'
Provides-Extra: full
Requires-Dist: aiosqlite; extra == 'full'
Requires-Dist: asyncify; extra == 'full'
Requires-Dist: av; extra == 'full'
Requires-Dist: ipython<8.19; extra == 'full'
Requires-Dist: python-dotenv; extra == 'full'
Requires-Dist: sqlalchemy[asyncio]; extra == 'full'
Requires-Dist: termcolor; extra == 'full'
Provides-Extra: shell
Requires-Dist: ipython<8.19; extra == 'shell'
Requires-Dist: python-dotenv; extra == 'shell'
Requires-Dist: termcolor; extra == 'shell'
Provides-Extra: tz
Requires-Dist: tzdata; extra == 'tz'
